{
	"objects":[{
		"gid":35000074,
		"x":11000,
		"objid":1000021},
	{
		"gid":35000074,
		"x":11000,
		"y":9000,
		"objid":1000024},
	{
		"gid":35000074,
		"x":11000,
		"y":3000,
		"objid":1000028},
	{
		"gid":35000074,
		"x":11000,
		"y":6000,
		"objid":1000029},
	{
		"gid":35000029,
		"x":9500,
		"y":2500,
		"objid":1000207},
	{
		"gid":35000029,
		"x":8500,
		"y":4500,
		"objid":1000208},
	{
		"gid":35000029,
		"x":8500,
		"y":7500,
		"objid":1000214},
	{
		"gid":35000029,
		"x":9500,
		"y":8500,
		"objid":1000217},
	{
		"gid":35000029,
		"x":9500,
		"y":9500,
		"objid":1000218},
	{
		"gid":35000029,
		"x":8500,
		"y":9500,
		"objid":1000219},
	{
		"gid":35000029,
		"x":2500,
		"y":7500,
		"objid":1000228},
	{
		"gid":35000029,
		"x":500,
		"y":6000,
		"objid":1000240},
	{
		"gid":35000029,
		"x":4500,
		"y":7500,
		"objid":1000241},
	{
		"gid":35000029,
		"x":3500,
		"y":7500,
		"objid":1000242},
	{
		"gid":35000029,
		"x":3500,
		"y":6500,
		"objid":1000243},
	{
		"gid":35000029,
		"x":5500,
		"y":7500,
		"objid":1000246},
	{
		"gid":35000029,
		"x":6500,
		"y":6500,
		"objid":1000248},
	{
		"gid":35000029,
		"x":7500,
		"y":6500,
		"objid":1000249},
	{
		"gid":35000029,
		"x":7500,
		"y":7500,
		"objid":1000250},
	{
		"gid":35000029,
		"x":4500,
		"y":5500,
		"objid":1000255},
	{
		"gid":35000029,
		"x":6500,
		"y":5500,
		"objid":1000259},
	{
		"gid":35000145,
		"x":5500,
		"y":5500,
		"objid":1000263},
	{
		"gid":35000145,
		"x":7500,
		"y":5500,
		"objid":1000264},
	{
		"gid":35000145,
		"x":9500,
		"y":3500,
		"objid":1000265},
	{
		"gid":35000145,
		"x":9500,
		"y":4500,
		"objid":1000266},
	{
		"gid":35000145,
		"x":9500,
		"y":6500,
		"objid":1000267},
	{
		"gid":35000145,
		"x":8500,
		"y":8500,
		"objid":1000268},
	{
		"gid":35000145,
		"x":9500,
		"y":7500,
		"objid":1000269},
	{
		"gid":35000145,
		"x":4500,
		"y":6500,
		"objid":1000270},
	{
		"gid":35000145,
		"x":500,
		"y":5000,
		"objid":1000271},
	{
		"gid":35000145,
		"x":1500,
		"y":5000,
		"objid":1000274},
	{
		"gid":35000030,
		"x":2500,
		"y":5500,
		"objid":1000278},
	{
		"gid":35000030,
		"x":2500,
		"y":6500,
		"objid":1000279},
	{
		"gid":35000030,
		"x":3500,
		"y":5500,
		"objid":1000281},
	{
		"gid":35000030,
		"x":1500,
		"y":6000,
		"objid":1000283},
	{
		"gid":35000030,
		"x":5500,
		"y":6500,
		"objid":1000286},
	{
		"gid":35000030,
		"x":8500,
		"y":6500,
		"objid":1000287},
	{
		"gid":35000030,
		"x":8500,
		"y":5500,
		"objid":1000288},
	{
		"gid":35000030,
		"x":9500,
		"y":5500,
		"objid":1000289},
	{
		"gid":35000039,
		"x":9000,
		"y":500,
		"objid":1000291},
	{
		"gid":35000161,
		"x":19000,
		"y":1500,
		"objid":1000295},
	{
		"gid":35000097,
		"x":19000,
		"y":5500,
		"objid":1000299},
	{
		"gid":35000096,
		"x":19000,
		"y":7000,
		"objid":1000302},
	{
		"gid":35000097,
		"x":17000,
		"y":8500,
		"objid":1000306},
	{
		"gid":35000097,
		"x":17000,
		"y":9500,
		"objid":1000307},
	{
		"gid":35000097,
		"x":17000,
		"y":10500,
		"objid":1000308},
	{
		"gid":35000047,
		"x":4500,
		"y":9500,
		"objid":1000336},
	{
		"gid":35000097,
		"x":19000,
		"y":4500,
		"objid":1000343},
	{
		"gid":35000097,
		"x":19000,
		"y":3500,
		"objid":1000344},
	{
		"gid":35000097,
		"x":19000,
		"y":2500,
		"objid":1000345},
	{
		"gid":35000008,
		"x":14500,
		"y":3000,
		"objid":1000346},
	{
		"gid":35000091,
		"x":15500,
		"y":1500,
		"objid":1000366},
	{
		"gid":35000091,
		"x":17500,
		"y":1500,
		"objid":1000374},
	{
		"gid":35000091,
		"x":16500,
		"y":1500,
		"objid":1000375},
	{
		"gid":35000091,
		"x":14500,
		"y":1500,
		"objid":1000378},
	{
		"gid":35000274,
		"x":19000,
		"y":1000,
		"objid":1000382},
	{
		"gid":35000446,
		"x":19000,
		"y":2000,
		"objid":1000386},
	{
		"gid":35000208,
		"x":6000,
		"y":2000,
		"objid":1000393},
	{
		"gid":35000319,
		"x":3000,
		"y":4000,
		"objid":1000395},
	{
		"gid":35000244,
		"x":8500,
		"y":-1000,
		"objid":1000398},
	{
		"gid":35000224,
		"x":1000,
		"y":2000,
		"objid":1000402},
	{
		"gid":35000223,
		"x":1000,
		"y":8000,
		"objid":1000406},
	{
		"gid":35000081,
		"x":16000,
		"y":4000,
		"objid":1000413},
	{
		"gid":35000081,
		"x":17000,
		"y":4000,
		"objid":1000414},
	{
		"gid":35000100,
		"x":17000,
		"y":7000,
		"objid":1000418},
	{
		"gid":35000081,
		"x":18000,
		"y":4000,
		"objid":1000421},
	{
		"gid":35000081,
		"x":16500,
		"y":3000,
		"objid":1000442},
	{
		"gid":35000081,
		"x":17500,
		"y":3000,
		"objid":1000443},
	{
		"gid":35000231,
		"x":1000,
		"y":6000,
		"objid":1000447},
	{
		"gid":35000245,
		"x":7000,
		"y":8000,
		"objid":1000449},
	{
		"gid":30000002,
		"x":14500,
		"y":4500,
		"objid":4000147,
		"card":49000001,
		"grid":59,
		"gpos_x":500,
		"gpos_y":500},
	{
		"gid":31000002,
		"x":15500,
		"y":8500,
		"objid":4000158,
		"lvl":4,
		"grid":67,
		"gpos_x":500,
		"gpos_y":500},
	{
		"gid":31000002,
		"x":14500,
		"y":8500,
		"objid":4000159,
		"lvl":4,
		"grid":68,
		"gpos_x":500,
		"gpos_y":500},
	{
		"gid":31000002,
		"x":13500,
		"y":8500,
		"objid":4000160,
		"lvl":4,
		"grid":69,
		"gpos_x":500,
		"gpos_y":500},
	{
		"gid":31000002,
		"x":12500,
		"y":8500,
		"objid":4000161,
		"lvl":4,
		"grid":70,
		"gpos_x":500,
		"gpos_y":500},
	{
		"gid":31000002,
		"x":18500,
		"y":8500,
		"objid":4000162,
		"lvl":4,
		"grid":71,
		"gpos_x":500,
		"gpos_y":500},
	{
		"gid":31000002,
		"x":19500,
		"y":8500,
		"objid":4000163,
		"lvl":4,
		"grid":72,
		"gpos_x":500,
		"gpos_y":500},
	{
		"gid":31000002,
		"x":20500,
		"y":8500,
		"objid":4000164,
		"lvl":4,
		"grid":73,
		"gpos_x":500,
		"gpos_y":500},
	{
		"gid":31000002,
		"x":20500,
		"y":7500,
		"objid":4000165,
		"lvl":4,
		"grid":74,
		"gpos_x":500,
		"gpos_y":500},
	{
		"gid":31000002,
		"x":20500,
		"y":6500,
		"objid":4000166,
		"lvl":4,
		"grid":75,
		"gpos_x":500,
		"gpos_y":500},
	{
		"gid":31000002,
		"x":20500,
		"y":4500,
		"objid":4000167,
		"lvl":4,
		"grid":76,
		"gpos_x":500,
		"gpos_y":500},
	{
		"gid":31000002,
		"x":20500,
		"y":5500,
		"objid":4000168,
		"lvl":4,
		"grid":77,
		"gpos_x":500,
		"gpos_y":500},
	{
		"gid":31000002,
		"x":20500,
		"y":2500,
		"objid":4000169,
		"lvl":4,
		"grid":78,
		"gpos_x":500,
		"gpos_y":500},
	{
		"gid":31000002,
		"x":20500,
		"y":3500,
		"objid":4000170,
		"lvl":4,
		"grid":79,
		"gpos_x":500,
		"gpos_y":500},
	{
		"gid":31000002,
		"x":20500,
		"y":1500,
		"objid":4000171,
		"lvl":4,
		"grid":80,
		"gpos_x":500,
		"gpos_y":500},
	{
		"gid":31000002,
		"x":20500,
		"y":500,
		"objid":4000172,
		"lvl":4,
		"grid":81,
		"gpos_x":500,
		"gpos_y":500},
	{
		"gid":31000002,
		"x":19500,
		"y":500,
		"objid":4000173,
		"lvl":4,
		"grid":82,
		"gpos_x":500,
		"gpos_y":500},
	{
		"gid":31000002,
		"x":18500,
		"y":500,
		"objid":4000174,
		"lvl":4,
		"grid":83,
		"gpos_x":500,
		"gpos_y":500},
	{
		"gid":31000002,
		"x":17500,
		"y":500,
		"objid":4000175,
		"lvl":4,
		"grid":84,
		"gpos_x":500,
		"gpos_y":500},
	{
		"gid":31000002,
		"x":16500,
		"y":500,
		"objid":4000176,
		"lvl":4,
		"grid":85,
		"gpos_x":500,
		"gpos_y":500},
	{
		"gid":31000002,
		"x":15500,
		"y":500,
		"objid":4000177,
		"lvl":4,
		"grid":86,
		"gpos_x":500,
		"gpos_y":500},
	{
		"gid":31000002,
		"x":14500,
		"y":500,
		"objid":4000178,
		"lvl":4,
		"grid":87,
		"gpos_x":500,
		"gpos_y":500},
	{
		"gid":31000002,
		"x":13500,
		"y":500,
		"objid":4000179,
		"lvl":4,
		"grid":88,
		"gpos_x":500,
		"gpos_y":500},
	{
		"gid":31000002,
		"x":12500,
		"y":500,
		"objid":4000180,
		"lvl":4,
		"grid":89,
		"gpos_x":500,
		"gpos_y":500},
	{
		"gid":31000002,
		"x":12500,
		"y":1500,
		"objid":4000181,
		"lvl":4,
		"grid":90,
		"gpos_x":500,
		"gpos_y":500},
	{
		"gid":31000002,
		"x":12500,
		"y":2500,
		"objid":4000182,
		"lvl":4,
		"grid":91,
		"gpos_x":500,
		"gpos_y":500},
	{
		"gid":31000002,
		"x":12500,
		"y":3500,
		"objid":4000183,
		"lvl":4,
		"grid":92,
		"gpos_x":500,
		"gpos_y":500},
	{
		"gid":31000002,
		"x":12500,
		"y":4500,
		"objid":4000184,
		"lvl":4,
		"grid":93,
		"gpos_x":500,
		"gpos_y":500},
	{
		"gid":31000002,
		"x":12500,
		"y":5500,
		"objid":4000185,
		"lvl":4,
		"grid":94,
		"gpos_x":500,
		"gpos_y":500},
	{
		"gid":31000002,
		"x":12500,
		"y":6500,
		"objid":4000186,
		"lvl":4,
		"grid":95,
		"gpos_x":500,
		"gpos_y":500},
	{
		"gid":31000002,
		"x":12500,
		"y":7500,
		"objid":4000187,
		"lvl":4,
		"grid":96,
		"gpos_x":500,
		"gpos_y":500},
	{
		"gid":30000003,
		"x":17000,
		"y":6000,
		"objid":4000190,
		"card":49000003,
		"grid":99,
		"gpos_x":1000,
		"gpos_y":1000}],
	"preview_attack":[{
		"gid":30000019,
		"x":7500,
		"y":4500,
		"objid":4000157,
		"card":49000012,
		"grid":66,
		"gpos_x":500,
		"gpos_y":500}],
	"env":{
		"id":16000000},
	
	"water":[20,1,41,1,41,1,41,1,41,1,41,1,41,1,41,1,41,1,41,1,41,1,41,1,41,1,41,1,41,1,41,1,41,1,41,1,41,1,41,1]}